mcp_connect_coze/__init__.py
mcp_connect_coze/connect_coze.py
mcp_connect-0.1.6.dist-info/METADATA
mcp_connect-0.1.6.dist-info/WHEEL
mcp_connect-0.1.6.dist-info/entry_points.txt
mcp_connect-0.1.6.dist-info/top_level.txt
mcp_connect-0.1.6.dist-info/RECORD
