Metadata-Version: 2.4
Name: mcp-connect
Version: 0.1.6
Summary: Coze-MCP 集成工具，将 Coze 智能体集成到 MCP 平台，实现流式对话功能
Author-email: MakeyFeng <405426648@qq.com>
License: MIT
Keywords: Coze,MCP,integration,streaming chat
Classifier: Programming Language :: Python :: 3.11
Classifier: Development Status :: 3 - Alpha
Classifier: License :: OSI Approved :: MIT License
Classifier: Operating System :: OS Independent
Requires-Python: >=3.11
Requires-Dist: annotated-types==0.7.0
Requires-Dist: anyio==4.9.0
Requires-Dist: authlib==1.6.0
Requires-Dist: build>=1.2.2.post1
Requires-Dist: certifi==2025.6.15
Requires-Dist: cffi==1.17.1
Requires-Dist: click==8.2.1
Requires-Dist: colorama==0.4.6
Requires-Dist: cozepy==0.16.2
Requires-Dist: cryptography==45.0.4
Requires-Dist: distro==1.9.0
Requires-Dist: h11==0.16.0
Requires-Dist: httpcore==1.0.9
Requires-Dist: httpx==0.27.2
Requires-Dist: httpx-sse==0.4.0
Requires-Dist: idna==3.10
Requires-Dist: markdown-it-py==3.0.0
Requires-Dist: mcp==1.9.4
Requires-Dist: mdurl==0.1.2
Requires-Dist: pycparser==2.22
Requires-Dist: pydantic==2.11.7
Requires-Dist: pydantic-core==2.33.2
Requires-Dist: pydantic-settings==2.9.1
Requires-Dist: pygments==2.19.1
Requires-Dist: python-dotenv==1.1.0
Requires-Dist: python-multipart==0.0.20
Requires-Dist: rich==14.0.0
Requires-Dist: shellingham==1.5.4
Requires-Dist: sniffio==1.3.1
Requires-Dist: sse-starlette==2.3.6
Requires-Dist: starlette==0.47.0
Requires-Dist: twine>=6.1.0
Requires-Dist: typer==0.16.0
Requires-Dist: typing-extensions==4.14.0
Requires-Dist: typing-inspection==0.4.1
Requires-Dist: uvicorn==0.34.3
Requires-Dist: websockets==14.2
